aivatar_project_widgets/__init__.py
aivatar_project_widgets/constants.py
aivatar_project_widgets/core.py
aivatar_project_widgets/icons/__init__.py
aivatar_project_widgets/icons/arrow-down-16.png
aivatar_project_widgets/icons/project-0-50.png
aivatar_project_widgets/icons/project@1x.png
aivatar_project_widgets/test/__init__.py
aivatar_project_widgets/test/test_core.py
aivatar_project_widgets/test/test_imports.py
aivatar_project_widgets-0.1.0.dist-info/METADATA
aivatar_project_widgets-0.1.0.dist-info/WHEEL
aivatar_project_widgets-0.1.0.dist-info/top_level.txt
aivatar_project_widgets-0.1.0.dist-info/RECORD
